mobileclip/__init__.py
mobileclip/clip.py
mobileclip/image_encoder.py
mobileclip/logger.py
mobileclip/text_encoder.py
mobileclip/configs/mobileclip_b.json
mobileclip/configs/mobileclip_s0.json
mobileclip/configs/mobileclip_s1.json
mobileclip/configs/mobileclip_s2.json
mobileclip/models/__init__.py
mobileclip/models/mci.py
mobileclip/models/vit.py
mobileclip/modules/__init__.py
mobileclip/modules/common/__init__.py
mobileclip/modules/common/mobileone.py
mobileclip/modules/common/transformer.py
mobileclip/modules/image/__init__.py
mobileclip/modules/image/image_projection.py
mobileclip/modules/image/replknet.py
mobileclip/modules/text/__init__.py
mobileclip/modules/text/repmixer.py
mobileclip/modules/text/tokenizer.py
visaionmobileclip-0.1.1.data/data/model-config/mobileclip_b.json
visaionmobileclip-0.1.1.data/data/model-config/mobileclip_s0.json
visaionmobileclip-0.1.1.data/data/model-config/mobileclip_s1.json
visaionmobileclip-0.1.1.data/data/model-config/mobileclip_s2.json
visaionmobileclip-0.1.1.dist-info/licenses/LICENSE
visaionmobileclip-0.1.1.dist-info/licenses/LICENSE_weights_data
visaionmobileclip-0.1.1.dist-info/METADATA
visaionmobileclip-0.1.1.dist-info/WHEEL
visaionmobileclip-0.1.1.dist-info/top_level.txt
visaionmobileclip-0.1.1.dist-info/RECORD
