Metadata-Version: 2.4
Name: visaionmobileclip
Version: 0.1.1
Summary: MobileCLIP
Home-page: https://github.com/apple/ml-mobileclip
Author: 
Author-email: 
Keywords: Mobile CLIP pretrained
Classifier: Development Status :: 3 - Alpha
Classifier: Intended Audience :: Education
Classifier: Intended Audience :: Science/Research
Classifier: Programming Language :: Python :: 3.7
Classifier: Programming Language :: Python :: 3.8
Classifier: Programming Language :: Python :: 3.9
Classifier: Programming Language :: Python :: 3.10
Classifier: Topic :: Scientific/Engineering
Classifier: Topic :: Scientific/Engineering :: Artificial Intelligence
Classifier: Topic :: Software Development
Classifier: Topic :: Software Development :: Libraries
Classifier: Topic :: Software Development :: Libraries :: Python Modules
Requires-Python: >=3.7
License-File: LICENSE
License-File: LICENSE_weights_data
Requires-Dist: open-clip-torch>=2.20.0
Requires-Dist: timm==0.9.5
Requires-Dist: torch>=2.1.0
Dynamic: classifier
Dynamic: home-page
Dynamic: keywords
Dynamic: license-file
Dynamic: requires-dist
Dynamic: requires-python
Dynamic: summary
